dimi/__init__.py
dimi/_integrations.py
dimi/_storage.py
dimi/_utils.py
dimi/dependency.py
dimi/di.py
dimi/exceptions.py
dimi/scopes.py
dimi-1.4.0.dist-info/LICENSE
dimi-1.4.0.dist-info/METADATA
dimi-1.4.0.dist-info/WHEEL
dimi-1.4.0.dist-info/top_level.txt
dimi-1.4.0.dist-info/RECORD
